propsim.py
propsim-0.0.5.dist-info/LICENSE
propsim-0.0.5.dist-info/METADATA
propsim-0.0.5.dist-info/WHEEL
propsim-0.0.5.dist-info/top_level.txt
propsim-0.0.5.dist-info/RECORD
