Metadata-Version: 2.1
Name: propsim
Version: 0.0.5
Summary: A simple and intuitive tool for simulating different types of aircraft engines.
Home-page: UNKNOWN
License: UNKNOWN
Platform: UNKNOWN
License-File: LICENSE
Requires-Dist: ambiance
Requires-Dist: pyyaml
